mib_generator/__init__.py
mib_generator/construction/TC_packet.py
mib_generator/construction/TC_packet_methods.py
mib_generator/construction/TM_packet.py
mib_generator/construction/TM_packet_methods.py
mib_generator/construction/__init__.py
mib_generator/construction/calib.py
mib_generator/data/__init__.py
mib_generator/data/config.json5
mib_generator/data/longdata.py
mib_generator/data/paths.json5
mib_generator/data/warn.py
mib_generator/generation/__init__.py
mib_generator/generation/gener.py
mib_generator/generation/gener_doc.py
mib_generator/generation/gener_methods.py
mib_generator/gui/__init__.py
mib_generator/gui/gui.py
mib_generator/gui/gui_methods.py
mib_generator/gui/ui_form.py
mib_generator/main/__init__.py
mib_generator/main/cli.py
mib_generator/main/main.py
mib_generator/parsing/__init__.py
mib_generator/parsing/load.py
mib_generator/parsing/par_cfile.py
mib_generator/parsing/par_header.py
mib_generator/parsing/par_methods.py
mib_generator/parsing/parser_main.py
mib_generator/temp/__init__.py
mib_generator/temp/config.json5
mib_generator/temp/paths.json5
mib_generator/temp/temp.py
mib_generator/utilities/__init__.py
mib_generator/utilities/data_gen.py
mib_generator/utilities/update.py
mib_generator/utilities/visualiser.py
mib_generator-0.1.3.dist-info/LICENSE
mib_generator-0.1.3.dist-info/METADATA
mib_generator-0.1.3.dist-info/WHEEL
mib_generator-0.1.3.dist-info/entry_points.txt
mib_generator-0.1.3.dist-info/top_level.txt
mib_generator-0.1.3.dist-info/zip-safe
mib_generator-0.1.3.dist-info/RECORD
