Metadata-Version: 2.1
Name: mib-generator
Version: 0.1.3
Summary: Generator of SCOS 2000 MIB databases.
Home-page: https://github.com/vachaj11/MIB-generator
Author: Josef Vácha
Author-email: josefvc16@gmail.com
License: MIT License
Classifier: Programming Language :: Python :: 3
Classifier: License :: OSI Approved :: MIT License
Classifier: Operating System :: OS Independent
Requires-Python: >=3.10
License-File: LICENSE
Requires-Dist: json5
Requires-Dist: PySide6
Requires-Dist: python-docx
